README.md
pyproject.toml
setup.cfg
setup.py
baseapp_comments/__init__.py
baseapp_comments/admin.py
baseapp_comments/apps.py
baseapp_comments/models.py
baseapp_comments/notifications.py
baseapp_comments/permissions.py
baseapp_comments/signals.py
baseapp_comments/validators.py
baseapp_comments.egg-info/PKG-INFO
baseapp_comments.egg-info/SOURCES.txt
baseapp_comments.egg-info/dependency_links.txt
baseapp_comments.egg-info/requires.txt
baseapp_comments.egg-info/top_level.txt
baseapp_comments/graphql/__init__.py
baseapp_comments/graphql/filters.py
baseapp_comments/graphql/mutations.py
baseapp_comments/graphql/object_types.py
baseapp_comments/graphql/queries.py
baseapp_comments/graphql/subscriptions.py
baseapp_comments/migrations/0001_initial.py
baseapp_comments/migrations/0002_alter_comment_user.py
baseapp_comments/migrations/0003_alter_comment_comments_count.py
baseapp_comments/migrations/0004_remove_comment_snapshot_insert_and_more.py
baseapp_comments/migrations/0005_remove_comment_snapshot_insert_and_more.py
baseapp_comments/migrations/0006_remove_comment_snapshot_insert_and_more.py
baseapp_comments/migrations/0007_remove_comment_insert_insert_and_more.py
baseapp_comments/migrations/0008_comment_new_profile_commentevent_new_profile_and_more.py
baseapp_comments/migrations/0009_migrate_profiles.py
baseapp_comments/migrations/0010_drop_profile_content_type.py
baseapp_comments/migrations/0011_rename_new_profile_to_profile.py
baseapp_comments/migrations/0012_alter_comment_options.py
baseapp_comments/migrations/0013_alter_commentevent_id.py
baseapp_comments/migrations/0014_alter_commentevent_pgh_context_and_more.py
baseapp_comments/migrations/0015_alter_commentevent_pgh_context_and_more.py
baseapp_comments/migrations/0016_remove_commentevent_in_reply_to_and_more.py
baseapp_comments/migrations/__init__.py
baseapp_comments/tests/__init__.py
baseapp_comments/tests/conftest.py
baseapp_comments/tests/factories.py
baseapp_comments/tests/test_comments_count.py
baseapp_comments/tests/test_graphql_mutations_create.py
baseapp_comments/tests/test_graphql_mutations_delete.py
baseapp_comments/tests/test_graphql_mutations_pin.py
