Metadata-Version: 2.1
Name: baseapp-comments
Version: 0.3.0
Summary: BaseApp Comments
Home-page: https://github.com/silverlogic/baseapp-backend
Author: The SilverLogic
Author-email: dev@tsl.io
License: BSD-3-Clause  # Example license
Platform: UNKNOWN
Requires-Python: >=3.6
